{"stem":"115320","instances":[{"docId":"Aachen_Prot_32","docUri":"Aachen_Prot_32.html","score":2,"contexts":[{"form":"115320","weight":"1","pos":5414,"context":"....ub.uni-frankfurt.de\/volltexte\/2010\/<mark>115320<\/mark>\/ (eingesehen am 27. Juli 2017).","fid":"note__4"},{"form":"115320","weight":"1","pos":5745,"context":"....ub.uni-frankfurt.de\/volltexte\/2010\/<mark>115320<\/mark>\/ (eingesehen am 27. Juli 2017).","fid":"note__3"}]},{"docId":"Aachen_Prot_26","docUri":"Aachen_Prot_26.html","score":1,"contexts":[{"form":"115320","weight":"1","pos":4331,"context":"....ub.uni-frankfurt.de\/volltexte\/2010\/<mark>115320<\/mark>\/ ","fid":"note__11"}]}]}