{"stem":"395","instances":[{"docId":"Aachen_Prot_26","docUri":"Aachen_Prot_26.html","score":5,"contexts":[{"form":"395","weight":"1","pos":4137,"context":"...8Köbler, Historisches Lexikon, S. 394–<mark>395<\/mark>.","fid":"note__2"},{"form":"395","weight":"1","pos":4141,"context":"9Köbler, Historisches Lexikon, S. <mark>395<\/mark>–396.","fid":"note__4"},{"form":"395","weight":"1","pos":4178,"context":".... Köbler, Historisches Lexikon, S. 394–<mark>395<\/mark>.","fid":"note__3"},{"form":"395","weight":"1","pos":4609,"context":"..., Ludwig I. In: NDB, Bd. 15, S. <mark>395<\/mark>–396.","fid":"note__4"},{"form":"395","weight":"1","pos":5130,"context":"..., Ludwig I. In: NDB, Bd. 15, S. <mark>395<\/mark>–396.","fid":"note__4"}]},{"docId":"Aachen_Prot_32","docUri":"Aachen_Prot_32.html","score":2,"contexts":[{"form":"395","weight":"1","pos":6187,"context":"..., Ludwig I. In: NDB, Bd. 15, S. <mark>395<\/mark>–396.","fid":"note__4"},{"form":"395","weight":"1","pos":6874,"context":"..., Ludwig I. In: NDB, Bd. 15, S. <mark>395<\/mark>–396.","fid":"note__4"}]},{"docId":"Aachen_Prot_41","docUri":"Aachen_Prot_41.html","score":2,"contexts":[{"form":"395","weight":"1","pos":4000,"context":"..., Ludwig I. In: NDB, Bd. 15, S. <mark>395<\/mark>–396.","fid":"note__4"},{"form":"395","weight":"1","pos":4094,"context":"..., Ludwig I. In: NDB, Bd. 15, S. <mark>395<\/mark>–396.","fid":"note__4"}]}]}