{"stem":"81820","instances":[{"docId":"Verona_I_16","docUri":"Verona_I_16.html","score":1,"contexts":[{"form":"81820","weight":"1","pos":638,"context":"<mark>81820<\/mark>\/21 Gesandter Frankreichs in München, 1822 Gesandter Frankreichs...","fid":"note__4"}]},{"docId":"Verona_I_6","docUri":"Verona_I_6.html","score":1,"contexts":[{"form":"81820","weight":"1","pos":1046,"context":"<mark>81820<\/mark> britischer Botschafter in Neapel, 1822 britischer Botschafter in...","fid":"note__4"}]},{"docId":"Verona_I_5","docUri":"Verona_I_5.html","score":1,"contexts":[{"form":"81820","weight":"1","pos":281,"context":"<mark>81820<\/mark>\/21 Gesandter Frankreichs in München, 1822 Gesandter Frankreichs...","fid":"note__4"}]}]}