{"stem":"affecté","instances":[{"docId":"Aachen_Prot_20","docUri":"Aachen_Prot_20.html","score":2,"contexts":[{"form":"affecté","weight":"1","pos":353,"context":"...sous silence que le Grand-Duc sera profondément <mark>affecté<\/mark> d’apprendre la Proposition de céder un Pays qu’Il gouverne...","fid":"p__8"},{"form":"affecté","weight":"1","pos":601,"context":"...se charger des rentes et pensions dont il est <mark>affecté<\/mark> en vertu de l’article 15 de l’Acte de...","fid":"p__25"}]},{"docId":"Verona_III_2","docUri":"Verona_III_2.html","score":1,"contexts":[{"form":"affecté","weight":"1","pos":740,"context":"...noire, et la manière dont il pourra être <mark>affecté<\/mark> par les règlemens de douane de la Porte,...","fid":"p__13"}]}]}