{"stem":"alexand","instances":[{"docId":"Aachen_Prot_32","docUri":"Aachen_Prot_32.html","score":6,"contexts":[{"form":"Alexander","weight":"1","pos":5330,"context":"...Aachen kursierten Gerüchte über eine geplante Entführung von Zar <mark>Alexander<\/mark>, die in Brüssel stattfinden sollte; vgl. Duchhardt...","fid":"note__6"},{"form":"Alexander","weight":"1","pos":6359,"context":"...Herzogin zu Mecklenburg-Strelitz, Ehefrau von Karl <mark>Alexander<\/mark> Fürst von Thurn und Taxis (1770–1827...","fid":"note__4"},{"form":"Alexander","weight":"1","pos":6404,"context":"66Vgl. Rey, <mark>Alexander<\/mark> I.; Schneider, Werner, Europa in Wien,...","fid":"note__4"},{"form":"Alexander","weight":"1","pos":6638,"context":"...Person den Eintrag zu Graf v. d. Pahlen Friedrich <mark>Alexander<\/mark> in der Erik-Amburger-Datenbank (Ausländer...","fid":"note__5"},{"form":"Alexander","weight":"1","pos":6738,"context":"90Vgl. Rey, <mark>Alexander<\/mark> I.; Schneider, Werner, Europa in Wien,...","fid":"note__4"},{"form":"Alexander","weight":"1","pos":6752,"context":"...Herzogin zu Mecklenburg-Strelitz, Ehefrau von Karl <mark>Alexander<\/mark> Fürst von Thurn und Taxis (1770–1827...","fid":"note__4"}]},{"docId":"Aachen_Prot_20","docUri":"Aachen_Prot_20.html","score":3,"contexts":[{"form":"Alexander","weight":"1","pos":2809,"context":"17 <mark>Alexander<\/mark> I. war mit Elisabeth Alexejevna, geb. Louise...","fid":"note__17"},{"form":"Alexander","weight":"1","pos":3162,"context":"40Vgl. Rey, <mark>Alexander<\/mark> I.; Schneider, Werner, Europa in Wien,...","fid":"note__4"},{"form":"Alexander","weight":"1","pos":3366,"context":"54Vgl. Rey, <mark>Alexander<\/mark> I.; Schneider, Werner, Europa in Wien,...","fid":"note__4"}]},{"docId":"Aachen_Prot_26","docUri":"Aachen_Prot_26.html","score":3,"contexts":[{"form":"Alexander","weight":"1","pos":4726,"context":"54Vgl. Rey, <mark>Alexander<\/mark> I.; Schneider, Werner, Europa in Wien,...","fid":"note__4"},{"form":"Alexander","weight":"1","pos":4930,"context":"...Herzogin zu Mecklenburg-Strelitz, Ehefrau von Karl <mark>Alexander<\/mark> Fürst von Thurn und Taxis (1770–1827...","fid":"note__4"},{"form":"Alexander","weight":"1","pos":4984,"context":"74Vgl. Rey, <mark>Alexander<\/mark> I.; Schneider, Werner, Europa in Wien,...","fid":"note__4"}]},{"docId":"Verona_V_2","docUri":"Verona_V_2.html","score":2,"contexts":[{"form":"Alexander","weight":"1","pos":4741,"context":"42Vgl. Rey, <mark>Alexander<\/mark> I.; Schneider, Werner, Europa in Wien,...","fid":"note__4"},{"form":"Alexander","weight":"1","pos":4798,"context":"47Vgl. Rey, <mark>Alexander<\/mark> I.; Schneider, Werner, Europa in Wien,...","fid":"note__4"}]},{"docId":"Aachen_Prot_21","docUri":"Aachen_Prot_21.html","score":2,"contexts":[{"form":"Alexander","weight":"1","pos":742,"context":"12Vgl. Jenkins, Baring, <mark>Alexander<\/mark>; Orbell, Baring, Alexander, first Baron...","fid":"note__4"},{"form":"Alexander","weight":"1","pos":745,"context":"..., Baring, Alexander; Orbell, Baring, <mark>Alexander<\/mark>, first Baron Ashburton. In: ODNB, Bd....","fid":"note__4"}]},{"docId":"Troppau_Prot_1","docUri":"Troppau_Prot_1.html","score":2,"contexts":[{"form":"Alexander","weight":"1","pos":4104,"context":"34Vgl. Rey, <mark>Alexander<\/mark> I.; Schneider, Werner, Europa in Wien,...","fid":"note__4"},{"form":"Alexander","weight":"1","pos":4331,"context":"46Vgl. Rey, <mark>Alexander<\/mark> I.; Schneider, Werner, Europa in Wien,...","fid":"note__4"}]},{"docId":"Troppau_Prot_6","docUri":"Troppau_Prot_6.html","score":2,"contexts":[{"form":"Alexander","weight":"1","pos":4645,"context":"29Vgl. Rey, <mark>Alexander<\/mark> I.; Schneider, Werner, Europa in Wien,...","fid":"note__4"},{"form":"Alexander","weight":"1","pos":4760,"context":"37Vgl. Rey, <mark>Alexander<\/mark> I.; Schneider, Werner, Europa in Wien,...","fid":"note__4"}]},{"docId":"Aachen_Prot_34","docUri":"Aachen_Prot_34.html","score":2,"contexts":[{"form":"Alexander","weight":"1","pos":2128,"context":"17Vgl. Rey, <mark>Alexander<\/mark> I.; Schneider, Werner, Europa in Wien,...","fid":"note__4"},{"form":"Alexander","weight":"1","pos":2172,"context":"21Vgl. Rey, <mark>Alexander<\/mark> I.; Schneider, Werner, Europa in Wien,...","fid":"note__4"}]},{"docId":"Laibach_Prot_1","docUri":"Laibach_Prot_1.html","score":2,"contexts":[{"form":"Alexander","weight":"1","pos":1002,"context":"13Vgl. Rey, <mark>Alexander<\/mark> I.; Schneider, Werner, Europa in Wien,...","fid":"note__4"},{"form":"Alexander","weight":"1","pos":1134,"context":"20Vgl. Rey, <mark>Alexander<\/mark> I.; Schneider, Werner, Europa in Wien,...","fid":"note__4"}]},{"docId":"Troppau_Prot_2","docUri":"Troppau_Prot_2.html","score":2,"contexts":[{"form":"Alexander","weight":"1","pos":3947,"context":"20Vgl. Rey, <mark>Alexander<\/mark> I.; Schneider, Werner, Europa in Wien,...","fid":"note__4"},{"form":"Alexander","weight":"1","pos":4190,"context":"35Vgl. Rey, <mark>Alexander<\/mark> I.; Schneider, Werner, Europa in Wien,...","fid":"note__4"}]},{"docId":"Aachen_Prot_29","docUri":"Aachen_Prot_29.html","score":2,"contexts":[{"form":"Alexander","weight":"1","pos":934,"context":"15Vgl. Jenkins, Baring, <mark>Alexander<\/mark>; Orbell, Baring, Alexander, first Baron...","fid":"note__4"},{"form":"Alexander","weight":"1","pos":937,"context":"..., Baring, Alexander; Orbell, Baring, <mark>Alexander<\/mark>, first Baron Ashburton. In: ODNB, Bd....","fid":"note__4"}]},{"docId":"Aachen_Prot_37","docUri":"Aachen_Prot_37.html","score":2,"contexts":[{"form":"Alexander","weight":"1","pos":1268,"context":"10Vgl. Jenkins, Baring, <mark>Alexander<\/mark>; Orbell, Baring, Alexander, first Baron...","fid":"note__4"},{"form":"Alexander","weight":"1","pos":1271,"context":"..., Baring, Alexander; Orbell, Baring, <mark>Alexander<\/mark>, first Baron Ashburton. In: ODNB, Bd....","fid":"note__4"}]},{"docId":"Verona_III_3","docUri":"Verona_III_3.html","score":2,"contexts":[{"form":"Alexander","weight":"1","pos":344,"context":"5Vgl. Rey, <mark>Alexander<\/mark> I.; Schneider, Werner, Europa in Wien,...","fid":"note__4"},{"form":"Alexander","weight":"1","pos":490,"context":"14Vgl. Rey, <mark>Alexander<\/mark> I.; Schneider, Werner, Europa in Wien,...","fid":"note__4"}]},{"docId":"Verona_I_22","docUri":"Verona_I_22.html","score":2,"contexts":[{"form":"Alexander","weight":"1","pos":2335,"context":"11Vgl. Rey, <mark>Alexander<\/mark> I.; Schneider, Werner, Europa in Wien,...","fid":"note__4"},{"form":"Alexander","weight":"1","pos":2385,"context":"16Vgl. Rey, <mark>Alexander<\/mark> I.; Schneider, Werner, Europa in Wien,...","fid":"note__4"}]},{"docId":"Verona_V_1","docUri":"Verona_V_1.html","score":2,"contexts":[{"form":"Alexander","weight":"1","pos":3329,"context":"20Vgl. Rey, <mark>Alexander<\/mark> I.; Schneider, Werner, Europa in Wien,...","fid":"note__4"},{"form":"Alexander","weight":"1","pos":3429,"context":"29Vgl. Rey, <mark>Alexander<\/mark> I.; Schneider, Werner, Europa in Wien,...","fid":"note__4"}]},{"docId":"Laibach_Prot_14","docUri":"Laibach_Prot_14.html","score":2,"contexts":[{"form":"Alexander","weight":"1","pos":1680,"context":"33Vgl. Rey, <mark>Alexander<\/mark> I.; Schneider, Werner, Europa in Wien,...","fid":"note__4"},{"form":"Alexander","weight":"1","pos":1767,"context":"38Vgl. Rey, <mark>Alexander<\/mark> I.; Schneider, Werner, Europa in Wien,...","fid":"note__4"}]},{"docId":"Aachen_Prot_9","docUri":"Aachen_Prot_9.html","score":2,"contexts":[{"form":"Alexander","weight":"1","pos":354,"context":"13Vgl. Jenkins, Baring, <mark>Alexander<\/mark>; Orbell, Baring, Alexander, first Baron...","fid":"note__4"},{"form":"Alexander","weight":"1","pos":357,"context":"..., Baring, Alexander; Orbell, Baring, <mark>Alexander<\/mark>, first Baron Ashburton. In: ODNB, Bd....","fid":"note__4"}]},{"docId":"Aachen_Prot_31","docUri":"Aachen_Prot_31.html","score":2,"contexts":[{"form":"Alexanders","weight":"1","pos":9330,"context":"24Erkärung Zar <mark>Alexanders<\/mark> I., Paris 31. März 1814; abgedruckt in BFSP...","fid":"note__6"},{"form":"Alexander","weight":"1","pos":10029,"context":"63Vgl. Rey, <mark>Alexander<\/mark> I.; Schneider, Werner, Europa in Wien,...","fid":"note__4"}]},{"docId":"Laibach_Prot_11","docUri":"Laibach_Prot_11.html","score":2,"contexts":[{"form":"Alexander","weight":"1","pos":1539,"context":"23Vgl. Rey, <mark>Alexander<\/mark> I.; Schneider, Werner, Europa in Wien,...","fid":"note__4"},{"form":"Alexander","weight":"1","pos":1761,"context":"35Vgl. Rey, <mark>Alexander<\/mark> I.; Schneider, Werner, Europa in Wien,...","fid":"note__4"}]},{"docId":"Verona_II_1","docUri":"Verona_II_1.html","score":2,"contexts":[{"form":"Alexander","weight":"1","pos":4364,"context":"14Vgl. Rey, <mark>Alexander<\/mark> I.; Schneider, Werner, Europa in Wien,...","fid":"note__4"},{"form":"Alexander","weight":"1","pos":4430,"context":"18Vgl. Rey, <mark>Alexander<\/mark> I.; Schneider, Werner, Europa in Wien,...","fid":"note__4"}]},{"docId":"Aachen_Prot_28","docUri":"Aachen_Prot_28.html","score":2,"contexts":[{"form":"Alexander","weight":"1","pos":4241,"context":"30Vgl. Rey, <mark>Alexander<\/mark> I.; Schneider, Werner, Europa in Wien,...","fid":"note__4"},{"form":"Alexander","weight":"1","pos":4296,"context":"34Vgl. Rey, <mark>Alexander<\/mark> I.; Schneider, Werner, Europa in Wien,...","fid":"note__4"}]},{"docId":"Laibach_Prot_16","docUri":"Laibach_Prot_16.html","score":2,"contexts":[{"form":"Alexander","weight":"1","pos":6700,"context":"39Vgl. Rey, <mark>Alexander<\/mark> I.; Schneider, Werner, Europa in Wien,...","fid":"note__4"},{"form":"Alexander","weight":"1","pos":6994,"context":"54Vgl. Rey, <mark>Alexander<\/mark> I.; Schneider, Werner, Europa in Wien,...","fid":"note__4"}]},{"docId":"Aachen_Prot_36","docUri":"Aachen_Prot_36.html","score":2,"contexts":[{"form":"Alexander","weight":"1","pos":606,"context":"14Vgl. Rey, <mark>Alexander<\/mark> I.; Schneider, Werner, Europa in Wien,...","fid":"note__4"},{"form":"Alexander","weight":"1","pos":761,"context":"26Vgl. Rey, <mark>Alexander<\/mark> I.; Schneider, Werner, Europa in Wien,...","fid":"note__4"}]},{"docId":"Verona_II_6","docUri":"Verona_II_6.html","score":2,"contexts":[{"form":"Alexander","weight":"1","pos":894,"context":"14Vgl. Rey, <mark>Alexander<\/mark> I.; Schneider, Werner, Europa in Wien,...","fid":"note__4"},{"form":"Alexander","weight":"1","pos":955,"context":"17Vgl. Rey, <mark>Alexander<\/mark> I.; Schneider, Werner, Europa in Wien,...","fid":"note__4"}]},{"docId":"Aachen_Prot_25","docUri":"Aachen_Prot_25.html","score":2,"contexts":[{"form":"Alexander","weight":"1","pos":2829,"context":"26Vgl. Rey, <mark>Alexander<\/mark> I.; Schneider, Werner, Europa in Wien,...","fid":"note__4"},{"form":"Alexander","weight":"1","pos":2896,"context":"30Vgl. Rey, <mark>Alexander<\/mark> I.; Schneider, Werner, Europa in Wien,...","fid":"note__4"}]},{"docId":"Aachen_Prot_6","docUri":"Aachen_Prot_6.html","score":2,"contexts":[{"form":"Alexander","weight":"1","pos":1309,"context":"11Vgl. Jenkins, Baring, <mark>Alexander<\/mark>; Orbell, Baring, Alexander, first Baron...","fid":"note__4"},{"form":"Alexander","weight":"1","pos":1312,"context":"..., Baring, Alexander; Orbell, Baring, <mark>Alexander<\/mark>, first Baron Ashburton. In: ODNB, Bd....","fid":"note__4"}]},{"docId":"Verona_III_1","docUri":"Verona_III_1.html","score":2,"contexts":[{"form":"Alexander","weight":"1","pos":2360,"context":"33Vgl. Rey, <mark>Alexander<\/mark> I.; Schneider, Werner, Europa in Wien,...","fid":"note__4"},{"form":"Alexander","weight":"1","pos":2568,"context":"47Vgl. Rey, <mark>Alexander<\/mark> I.; Schneider, Werner, Europa in Wien,...","fid":"note__4"}]},{"docId":"Aachen_Prot_41","docUri":"Aachen_Prot_41.html","score":2,"contexts":[{"form":"Alexander","weight":"1","pos":3772,"context":"28Vgl. Rey, <mark>Alexander<\/mark> I.; Schneider, Werner, Europa in Wien,...","fid":"note__4"},{"form":"Alexander","weight":"1","pos":4043,"context":"47Vgl. Rey, <mark>Alexander<\/mark> I.; Schneider, Werner, Europa in Wien,...","fid":"note__4"}]},{"docId":"Verona_I_9","docUri":"Verona_I_9.html","score":2,"contexts":[{"form":"Alexander","weight":"1","pos":280,"context":"4Vgl. Rey, <mark>Alexander<\/mark> I.; Schneider, Werner, Europa in Wien,...","fid":"note__4"},{"form":"Alexander","weight":"1","pos":359,"context":"10Vgl. Rey, <mark>Alexander<\/mark> I.; Schneider, Werner, Europa in Wien,...","fid":"note__4"}]},{"docId":"Verona_I_4","docUri":"Verona_I_4.html","score":2,"contexts":[{"form":"Alexander","weight":"1","pos":665,"context":"7Vgl. Rey, <mark>Alexander<\/mark> I.; Schneider, Werner, Europa in Wien,...","fid":"note__4"},{"form":"Alexander","weight":"1","pos":742,"context":"13Vgl. Rey, <mark>Alexander<\/mark> I.; Schneider, Werner, Europa in Wien,...","fid":"note__4"}]},{"docId":"Troppau_Prot_4","docUri":"Troppau_Prot_4.html","score":2,"contexts":[{"form":"Alexander","weight":"1","pos":2079,"context":"19Vgl. Rey, <mark>Alexander<\/mark> I.; Schneider, Werner, Europa in Wien,...","fid":"note__4"},{"form":"Alexander","weight":"1","pos":2240,"context":"27Vgl. Rey, <mark>Alexander<\/mark> I.; Schneider, Werner, Europa in Wien,...","fid":"note__4"}]},{"docId":"Aachen_Prot_39","docUri":"Aachen_Prot_39.html","score":2,"contexts":[{"form":"Alexander","weight":"1","pos":3642,"context":"23Vgl. Rey, <mark>Alexander<\/mark> I.; Schneider, Werner, Europa in Wien,...","fid":"note__4"},{"form":"Alexander","weight":"1","pos":3711,"context":"29Vgl. Rey, <mark>Alexander<\/mark> I.; Schneider, Werner, Europa in Wien,...","fid":"note__4"}]},{"docId":"Aachen_Dok_50","docUri":"Aachen_Dok_50.html","score":2,"contexts":[{"form":"Alexander","weight":"1","pos":3875,"context":"9Vgl. Rey, <mark>Alexander<\/mark> I.; Schneider, Werner, Europa in Wien,...","fid":"note__4"},{"form":"Alexander","weight":"1","pos":4039,"context":"19Vgl. Rey, <mark>Alexander<\/mark> I.; Schneider, Werner, Europa in Wien,...","fid":"note__4"}]},{"docId":"Aachen_Prot_17","docUri":"Aachen_Prot_17.html","score":2,"contexts":[{"form":"Alexander","weight":"1","pos":735,"context":"24Vgl. Rey, <mark>Alexander<\/mark> I.; Schneider, Werner, Europa in Wien,...","fid":"note__4"},{"form":"Alexander","weight":"1","pos":774,"context":"27Vgl. Rey, <mark>Alexander<\/mark> I.; Schneider, Werner, Europa in Wien,...","fid":"note__4"}]},{"docId":"Verona_III_2","docUri":"Verona_III_2.html","score":2,"contexts":[{"form":"Alexander","weight":"1","pos":1019,"context":"13Vgl. Rey, <mark>Alexander<\/mark> I.; Schneider, Werner, Europa in Wien,...","fid":"note__4"},{"form":"Alexander","weight":"1","pos":1255,"context":"28Vgl. Rey, <mark>Alexander<\/mark> I.; Schneider, Werner, Europa in Wien,...","fid":"note__4"}]},{"docId":"Aachen_Prot_5","docUri":"Aachen_Prot_5.html","score":2,"contexts":[{"form":"Alexander","weight":"1","pos":1975,"context":"19Vgl. Rey, <mark>Alexander<\/mark> I.; Schneider, Werner, Europa in Wien,...","fid":"note__4"},{"form":"Alexander","weight":"1","pos":2039,"context":"23Vgl. Rey, <mark>Alexander<\/mark> I.; Schneider, Werner, Europa in Wien,...","fid":"note__4"}]},{"docId":"Troppau_Prot_3","docUri":"Troppau_Prot_3.html","score":2,"contexts":[{"form":"Alexander","weight":"1","pos":6309,"context":"31Vgl. Rey, <mark>Alexander<\/mark> I.; Schneider, Werner, Europa in Wien,...","fid":"note__4"},{"form":"Alexander","weight":"1","pos":6592,"context":"47Vgl. Rey, <mark>Alexander<\/mark> I.; Schneider, Werner, Europa in Wien,...","fid":"note__4"}]},{"docId":"Laibach_Prot_9","docUri":"Laibach_Prot_9.html","score":2,"contexts":[{"form":"Alexander","weight":"1","pos":5861,"context":"41Vgl. Rey, <mark>Alexander<\/mark> I.; Schneider, Werner, Europa in Wien,...","fid":"note__4"},{"form":"Alexander","weight":"1","pos":5985,"context":"49Vgl. Rey, <mark>Alexander<\/mark> I.; Schneider, Werner, Europa in Wien,...","fid":"note__4"}]},{"docId":"Laibach_Prot_12","docUri":"Laibach_Prot_12.html","score":1,"contexts":[{"form":"Alexander","weight":"1","pos":1311,"context":"30Vgl. Rey, <mark>Alexander<\/mark> I.; Schneider, Werner, Europa in Wien,...","fid":"note__4"}]},{"docId":"Verona_I_12","docUri":"Verona_I_12.html","score":1,"contexts":[{"form":"Alexander","weight":"1","pos":1687,"context":"13Vgl. Rey, <mark>Alexander<\/mark> I.; Schneider, Werner, Europa in Wien,...","fid":"note__4"}]},{"docId":"Laibach_Prot_3","docUri":"Laibach_Prot_3.html","score":1,"contexts":[{"form":"Alexander","weight":"1","pos":606,"context":"17Vgl. Rey, <mark>Alexander<\/mark> I.; Schneider, Werner, Europa in Wien,...","fid":"note__4"}]},{"docId":"Laibach_Prot_13","docUri":"Laibach_Prot_13.html","score":1,"contexts":[{"form":"Alexander","weight":"1","pos":1310,"context":"27Vgl. Rey, <mark>Alexander<\/mark> I.; Schneider, Werner, Europa in Wien,...","fid":"note__4"}]},{"docId":"Aachen_Prot_1","docUri":"Aachen_Prot_1.html","score":1,"contexts":[{"form":"Alexander","weight":"1","pos":609,"context":"20Vgl. Rey, <mark>Alexander<\/mark> I.; Schneider, Werner, Europa in Wien,...","fid":"note__4"}]},{"docId":"Troppau_Prot_7","docUri":"Troppau_Prot_7.html","score":1,"contexts":[{"form":"Alexander","weight":"1","pos":5662,"context":"48Vgl. Rey, <mark>Alexander<\/mark> I.; Schneider, Werner, Europa in Wien,...","fid":"note__4"}]},{"docId":"Verona_I_21","docUri":"Verona_I_21.html","score":1,"contexts":[{"form":"Alexander","weight":"1","pos":1032,"context":"10Vgl. Rey, <mark>Alexander<\/mark> I.; Schneider, Werner, Europa in Wien,...","fid":"note__4"}]},{"docId":"Verona_I_16","docUri":"Verona_I_16.html","score":1,"contexts":[{"form":"Alexander","weight":"1","pos":932,"context":"25Vgl. Rey, <mark>Alexander<\/mark> I.; Schneider, Werner, Europa in Wien,...","fid":"note__4"}]},{"docId":"Aachen_Prot_30","docUri":"Aachen_Prot_30.html","score":1,"contexts":[{"form":"Alexander","weight":"1","pos":3194,"context":"29Vgl. Rey, <mark>Alexander<\/mark> I.; Schneider, Werner, Europa in Wien,...","fid":"note__4"}]},{"docId":"Laibach_Prot_5","docUri":"Laibach_Prot_5.html","score":1,"contexts":[{"form":"Alexander","weight":"1","pos":856,"context":"21Vgl. Rey, <mark>Alexander<\/mark> I.; Schneider, Werner, Europa in Wien,...","fid":"note__4"}]},{"docId":"Laibach_Prot_6","docUri":"Laibach_Prot_6.html","score":1,"contexts":[{"form":"Alexander","weight":"1","pos":1008,"context":"23Vgl. Rey, <mark>Alexander<\/mark> I.; Schneider, Werner, Europa in Wien,...","fid":"note__4"}]},{"docId":"Laibach_Prot_4","docUri":"Laibach_Prot_4.html","score":1,"contexts":[{"form":"Alexander","weight":"1","pos":1310,"context":"18Vgl. Rey, <mark>Alexander<\/mark> I.; Schneider, Werner, Europa in Wien,...","fid":"note__4"}]},{"docId":"Laibach_Prot_7","docUri":"Laibach_Prot_7.html","score":1,"contexts":[{"form":"Alexander","weight":"1","pos":716,"context":"23Vgl. Rey, <mark>Alexander<\/mark> I.; Schneider, Werner, Europa in Wien,...","fid":"note__4"}]},{"docId":"Aachen_Prot_43","docUri":"Aachen_Prot_43.html","score":1,"contexts":[{"form":"Alexander","weight":"1","pos":588,"context":"15Vgl. Rey, <mark>Alexander<\/mark> I.; Schneider, Werner, Europa in Wien,...","fid":"note__4"}]},{"docId":"Verona_II_3","docUri":"Verona_II_3.html","score":1,"contexts":[{"form":"Alexander","weight":"1","pos":896,"context":"11Vgl. Rey, <mark>Alexander<\/mark> I.; Schneider, Werner, Europa in Wien,...","fid":"note__4"}]},{"docId":"Verona_II_8","docUri":"Verona_II_8.html","score":1,"contexts":[{"form":"Alexander","weight":"1","pos":1065,"context":"16Vgl. Rey, <mark>Alexander<\/mark> I.; Schneider, Werner, Europa in Wien,...","fid":"note__4"}]},{"docId":"Verona_II_7","docUri":"Verona_II_7.html","score":1,"contexts":[{"form":"Alexander","weight":"1","pos":2246,"context":"28Vgl. Rey, <mark>Alexander<\/mark> I.; Schneider, Werner, Europa in Wien,...","fid":"note__4"}]},{"docId":"Laibach_Prot_2","docUri":"Laibach_Prot_2.html","score":1,"contexts":[{"form":"Alexander","weight":"1","pos":287,"context":"6Vgl. Rey, <mark>Alexander<\/mark> I.; Schneider, Werner, Europa in Wien,...","fid":"note__4"}]},{"docId":"Verona_IX_1","docUri":"Verona_IX_1.html","score":1,"contexts":[{"form":"Alexander","weight":"1","pos":3446,"context":"14Vgl. Rey, <mark>Alexander<\/mark> I.; Schneider, Werner, Europa in Wien,...","fid":"note__4"}]},{"docId":"Aachen_Prot_33","docUri":"Aachen_Prot_33.html","score":1,"contexts":[{"form":"Alexander","weight":"1","pos":1509,"context":"17Vgl. Rey, <mark>Alexander<\/mark> I.; Schneider, Werner, Europa in Wien,...","fid":"note__4"}]},{"docId":"Verona_II_2","docUri":"Verona_II_2.html","score":1,"contexts":[{"form":"Alexander","weight":"1","pos":830,"context":"17Vgl. Rey, <mark>Alexander<\/mark> I.; Schneider, Werner, Europa in Wien,...","fid":"note__4"}]},{"docId":"Verona_I_17","docUri":"Verona_I_17.html","score":1,"contexts":[{"form":"Alexander","weight":"1","pos":866,"context":"10Vgl. Rey, <mark>Alexander<\/mark> I.; Schneider, Werner, Europa in Wien,...","fid":"note__4"}]},{"docId":"Verona_I_1","docUri":"Verona_I_1.html","score":1,"contexts":[{"form":"Alexander","weight":"1","pos":1514,"context":"12Vgl. Rey, <mark>Alexander<\/mark> I.; Schneider, Werner, Europa in Wien,...","fid":"note__4"}]},{"docId":"Troppau_Prot_8","docUri":"Troppau_Prot_8.html","score":1,"contexts":[{"form":"Alexander","weight":"1","pos":1515,"context":"19Vgl. Rey, <mark>Alexander<\/mark> I.; Schneider, Werner, Europa in Wien,...","fid":"note__4"}]},{"docId":"Aachen_Prot_24","docUri":"Aachen_Prot_24.html","score":1,"contexts":[{"form":"Alexander","weight":"1","pos":567,"context":"8Vgl. Rey, <mark>Alexander<\/mark> I.; Schneider, Werner, Europa in Wien,...","fid":"note__4"}]},{"docId":"Troppau_Prot_5","docUri":"Troppau_Prot_5.html","score":1,"contexts":[{"form":"Alexander","weight":"1","pos":3158,"context":"29Vgl. Rey, <mark>Alexander<\/mark> I.; Schneider, Werner, Europa in Wien,...","fid":"note__4"}]},{"docId":"Laibach_Prot_8","docUri":"Laibach_Prot_8.html","score":1,"contexts":[{"form":"Alexander","weight":"1","pos":2556,"context":"29Vgl. Rey, <mark>Alexander<\/mark> I.; Schneider, Werner, Europa in Wien,...","fid":"note__4"}]},{"docId":"Laibach_Prot_10","docUri":"Laibach_Prot_10.html","score":1,"contexts":[{"form":"Alexander","weight":"1","pos":1160,"context":"31Vgl. Rey, <mark>Alexander<\/mark> I.; Schneider, Werner, Europa in Wien,...","fid":"note__4"}]},{"docId":"Verona_II_5","docUri":"Verona_II_5.html","score":1,"contexts":[{"form":"Alexander","weight":"1","pos":1471,"context":"28Vgl. Rey, <mark>Alexander<\/mark> I.; Schneider, Werner, Europa in Wien,...","fid":"note__4"}]},{"docId":"Aachen_Prot_42","docUri":"Aachen_Prot_42.html","score":1,"contexts":[{"form":"Alexander","weight":"1","pos":819,"context":"25Vgl. Rey, <mark>Alexander<\/mark> I.; Schneider, Werner, Europa in Wien,...","fid":"note__4"}]}]}