{"stem":"analysiert","instances":[{"docId":"Aachen_Prot_12","docUri":"Aachen_Prot_12.html","score":1,"contexts":[{"form":"analysiert","weight":"1","pos":154,"context":"...in Hinblick auf den Konflikt zwischen Spanien und Portugal <mark>analysiert<\/mark>.","fid":"note__5"}]},{"docId":"Aachen_Prot_48","docUri":"Aachen_Prot_48.html","score":1,"contexts":[{"form":"analysiert","weight":"1","pos":243,"context":"...in Hinblick auf den Konflikt zwischen Spanien und Portugal <mark>analysiert<\/mark>.","fid":"note__4"}]}]}