{"stem":"bde","instances":[{"docId":"Aachen_Prot_26","docUri":"Aachen_Prot_26.html","score":3,"contexts":[{"form":"Bde","weight":"1","pos":4210,"context":"...de l’Europe depuis la paix de Westphalie. 15 <mark>Bde<\/mark>. (Paris 1816–1818).","fid":"note__5"},{"form":"Bde","weight":"1","pos":4862,"context":"...; Tulard, Napoleon; Broers, Napoleon (2 <mark>Bde<\/mark>.).","fid":"note__4"},{"form":"Bde","weight":"1","pos":5006,"context":"...; Tulard, Napoleon; Broers, Napoleon (2 <mark>Bde<\/mark>.).","fid":"note__4"}]},{"docId":"Troppau_Prot_7","docUri":"Troppau_Prot_7.html","score":2,"contexts":[{"form":"Bde","weight":"1","pos":5759,"context":"...; Tulard, Napoleon; Broers, Napoleon (2 <mark>Bde<\/mark>.).","fid":"note__4"},{"form":"Bde","weight":"1","pos":5802,"context":"...; Tulard, Napoleon; Broers, Napoleon (2 <mark>Bde<\/mark>.).","fid":"note__4"}]},{"docId":"Verona_I_21","docUri":"Verona_I_21.html","score":2,"contexts":[{"form":"Bde","weight":"1","pos":1054,"context":"...; Tulard, Napoleon; Broers, Napoleon (2 <mark>Bde<\/mark>.).","fid":"note__4"},{"form":"Bde","weight":"1","pos":1103,"context":"...; Tulard, Napoleon; Broers, Napoleon (2 <mark>Bde<\/mark>.).","fid":"note__4"}]},{"docId":"Aachen_Prot_31","docUri":"Aachen_Prot_31.html","score":2,"contexts":[{"form":"Bde","weight":"1","pos":9788,"context":"...; Tulard, Napoleon; Broers, Napoleon (2 <mark>Bde<\/mark>.).","fid":"note__4"},{"form":"Bde","weight":"1","pos":10200,"context":"...; Tulard, Napoleon; Broers, Napoleon (2 <mark>Bde<\/mark>.).","fid":"note__4"}]},{"docId":"Aachen_Prot_43","docUri":"Aachen_Prot_43.html","score":2,"contexts":[{"form":"Bde","weight":"1","pos":433,"context":"...; Tulard, Napoleon; Broers, Napoleon (2 <mark>Bde<\/mark>.).","fid":"note__4"},{"form":"Bde","weight":"1","pos":700,"context":"...; Tulard, Napoleon; Broers, Napoleon (2 <mark>Bde<\/mark>.).","fid":"note__4"}]},{"docId":"Aachen_Dok_50","docUri":"Aachen_Dok_50.html","score":2,"contexts":[{"form":"Bde","weight":"1","pos":3907,"context":"...; Tulard, Napoleon; Broers, Napoleon (2 <mark>Bde<\/mark>.).","fid":"note__4"},{"form":"Bde","weight":"1","pos":4061,"context":"...; Tulard, Napoleon; Broers, Napoleon (2 <mark>Bde<\/mark>.).","fid":"note__4"}]},{"docId":"Troppau_Prot_3","docUri":"Troppau_Prot_3.html","score":2,"contexts":[{"form":"Bde","weight":"1","pos":6415,"context":"...; Tulard, Napoleon; Broers, Napoleon (2 <mark>Bde<\/mark>.).","fid":"note__4"},{"form":"Bde","weight":"1","pos":6620,"context":"...; Tulard, Napoleon; Broers, Napoleon (2 <mark>Bde<\/mark>.).","fid":"note__4"}]},{"docId":"Troppau_Prot_5","docUri":"Troppau_Prot_5.html","score":2,"contexts":[{"form":"Bde","weight":"1","pos":3186,"context":"...; Tulard, Napoleon; Broers, Napoleon (2 <mark>Bde<\/mark>.).","fid":"note__4"},{"form":"Bde","weight":"1","pos":3326,"context":"...; Tulard, Napoleon; Broers, Napoleon (2 <mark>Bde<\/mark>.).","fid":"note__4"}]},{"docId":"Verona_V_2","docUri":"Verona_V_2.html","score":1,"contexts":[{"form":"Bde","weight":"1","pos":4763,"context":"...; Tulard, Napoleon; Broers, Napoleon (2 <mark>Bde<\/mark>.).","fid":"note__4"}]},{"docId":"Troppau_Prot_1","docUri":"Troppau_Prot_1.html","score":1,"contexts":[{"form":"Bde","weight":"1","pos":4316,"context":"...; Tulard, Napoleon; Broers, Napoleon (2 <mark>Bde<\/mark>.).","fid":"note__4"}]},{"docId":"Troppau_Prot_2","docUri":"Troppau_Prot_2.html","score":1,"contexts":[{"form":"Bde","weight":"1","pos":4121,"context":"...; Tulard, Napoleon; Broers, Napoleon (2 <mark>Bde<\/mark>.).","fid":"note__4"}]},{"docId":"Aachen_Prot_32","docUri":"Aachen_Prot_32.html","score":1,"contexts":[{"form":"Bde","weight":"1","pos":6580,"context":"...; Tulard, Napoleon; Broers, Napoleon (2 <mark>Bde<\/mark>.).","fid":"note__4"}]},{"docId":"Aachen_Prot_20","docUri":"Aachen_Prot_20.html","score":1,"contexts":[{"form":"Bde","weight":"1","pos":3218,"context":"...; Tulard, Napoleon; Broers, Napoleon (2 <mark>Bde<\/mark>.).","fid":"note__4"}]}]}