{"stem":"chaumont","instances":[{"docId":"Aachen_Prot_33","docUri":"Aachen_Prot_33.html","score":3,"contexts":[{"form":"Chaumont","weight":"1","pos":914,"context":"...les articles 7, 8 et 12 du Traité de <mark>Chaumont<\/mark>, il est entendu que, le cas prévu...","fid":"p__10"},{"form":"Chaumont","weight":"1","pos":934,"context":"...mois, indiqué dans l’article 8 du traité de <mark>Chaumont<\/mark>, comme celui où le corps auxiliaire serait prêt...","fid":"p__10"},{"form":"Chaumont","weight":"1","pos":978,"context":"...le terme fixé par l’article 8 du Traité de <mark>Chaumont<\/mark> comme ci-dessus expliqué, et le corps russe...","fid":"p__11"}]}]}