{"stem":"chute","instances":[{"docId":"Troppau_Prot_6","docUri":"Troppau_Prot_6.html","score":1,"contexts":[{"form":"chute","weight":"1","pos":3851,"context":"...social, l’église a bientôt été entrainée dans sa <mark>chute<\/mark>.","fid":"p__28"}]},{"docId":"Laibach_Prot_16","docUri":"Laibach_Prot_16.html","score":1,"contexts":[{"form":"chute","weight":"1","pos":3095,"context":"...n’est resté de cette révolution, calculée sur la <mark>chute<\/mark> de plus d’un gouvernement que les souvenirs honteux emportés...","fid":"p__18"}]}]}