{"stem":"complex","instances":[{"docId":"Verona_V_2","docUri":"Verona_V_2.html","score":1,"contexts":[{"form":"complexe","weight":"1","pos":1523,"context":"...une prudente lenteur dans une affaire d’une nature si <mark>complexe<\/mark> ; un article additionnel de cette Convention accordait un...","fid":"p__26"}]},{"docId":"Verona_I_1","docUri":"Verona_I_1.html","score":1,"contexts":[{"form":"complexe","weight":"1","pos":1041,"context":"...dans telle position donnée est au contraire une question <mark>complexe<\/mark> et difficile, par laquelle le rétablissement de l’ordre...","fid":"p__28"}]}]}