{"stem":"cruiser","instances":[{"docId":"Aachen_Prot_23","docUri":"Aachen_Prot_23.html","score":2,"contexts":[{"form":"Cruisers","weight":"1","pos":1657,"context":"...the great maritime States adopt the Principle, their <mark>Cruisers<\/mark> form but one Squadron against the illicit Slave Traders...","fid":"p__37"},{"form":"Cruisers","weight":"1","pos":1687,"context":"...would be considerably to multiply the number of the <mark>Cruisers<\/mark>, consequently the chance of Captures, whilst it...","fid":"p__37"}]}]}