{"stem":"d'exempl","instances":[{"docId":"Troppau_Prot_1","docUri":"Troppau_Prot_1.html","score":1,"contexts":[{"form":"d’exemple","weight":"1","pos":1188,"context":"...activité va en croissant. Non seulement elle prêche <mark>d’exemple<\/mark>, mais ses émissaires parcourent l’Italie entière ; elle...","fid":"p__17"}]},{"docId":"Aachen_Prot_31","docUri":"Aachen_Prot_31.html","score":1,"contexts":[{"form":"d’exemple","weight":"1","pos":1079,"context":"...jamais enfreints par cette dernière. Il n’existe point <mark>d’exemple<\/mark> que la Porte n’ait satisfait à l’indemnité pleine et...","fid":"p__19"}]}]}