{"stem":"désuétud","instances":[{"docId":"Aachen_Prot_32","docUri":"Aachen_Prot_32.html","score":1,"contexts":[{"form":"désuétude","weight":"1","pos":1373,"context":"...que même cet article ne finisse par tomber en <mark>désuétude<\/mark> si les souvenirs de leur existence indépendante et souveraine...","fid":"p__21"}]},{"docId":"Verona_II_1","docUri":"Verona_II_1.html","score":1,"contexts":[{"form":"désuétude","weight":"1","pos":2847,"context":"...un grand nombre de règlemens ignorés ou tombés en <mark>désuétude<\/mark>, et offrait de l’autre de grandes lacunes :...","fid":"p__53"}]}]}