{"stem":"ehemalig","instances":[{"docId":"Aachen_Prot_32","docUri":"Aachen_Prot_32.html","score":4,"contexts":[{"form":"ehemalige","weight":"1","pos":5664,"context":"...1784–1860) regiert. Es umfasste zahlreiche <mark>ehemalige<\/mark> Reichsgebiete, Hauptstad war Kassel; vgl. Todorov...","fid":"note__5"},{"form":"ehemalige","weight":"1","pos":5825,"context":"...1784–1860) regiert. Es umfasste zahlreiche <mark>ehemalige<\/mark> Reichsgebiete, Hauptstad war Kassel; vgl. Todorov...","fid":"note__7"},{"form":"Ehemaliger","weight":"1","pos":6656,"context":"84<mark>Ehemaliger<\/mark> König von Westphalen; vgl. zu seiner Person...","fid":"note__4"},{"form":"Ehemaliger","weight":"1","pos":6831,"context":"97<mark>Ehemaliger<\/mark> König von Westphalen; vgl. zu seiner Person...","fid":"note__4"}]},{"docId":"Verona_VII_1","docUri":"Verona_VII_1.html","score":4,"contexts":[{"form":"ehemalige","weight":"1","pos":189,"context":"3Geb. Prinzessin von Württemberg, <mark>ehemalige<\/mark> Königin von Westphalen; vgl. zu ihrer Person...","fid":"note__4"},{"form":"Ehemaliger","weight":"1","pos":206,"context":"4<mark>Ehemaliger<\/mark> König von Westphalen; vgl. zu seiner Person...","fid":"note__4"},{"form":"Ehemaliger","weight":"1","pos":337,"context":"11<mark>Ehemaliger<\/mark> König von Westphalen; vgl. zu seiner Person...","fid":"note__4"},{"form":"ehemalige","weight":"1","pos":364,"context":"12Geb. Prinzessin von Württemberg, <mark>ehemalige<\/mark> Königin von Westphalen; vgl. zu ihrer Person...","fid":"note__4"}]},{"docId":"Verona_II_7","docUri":"Verona_II_7.html","score":2,"contexts":[{"form":"Ehemalige","weight":"1","pos":2369,"context":"35<mark>Ehemalige<\/mark> Kaiserin der Franzosen; vgl. zu ihrer Person...","fid":"note__4"},{"form":"Ehemalige","weight":"1","pos":2480,"context":"40<mark>Ehemalige<\/mark> Kaiserin der Franzosen; vgl. zu ihrer Person...","fid":"note__4"}]},{"docId":"Aachen_Prot_31","docUri":"Aachen_Prot_31.html","score":1,"contexts":[{"form":"ehemaliger","weight":"1","pos":10090,"context":"67Napoleons <mark>ehemaliger<\/mark> Ordonnanzoffizier, während der 100 Tage sein Generaladjutant;...","fid":"note__4"}]}]}