{"stem":"henri","instances":[{"docId":"Aachen_Prot_31","docUri":"Aachen_Prot_31.html","score":2,"contexts":[{"form":"Henry","weight":"1","pos":10112,"context":"...vgl. zu seiner Person Thompson, Bathurst, <mark>Henry<\/mark>, third Earl Bathurst. In: ODNB, Bd....","fid":"note__4"},{"form":"Henry","weight":"1","pos":10312,"context":"...vgl. zu seiner Person Thompson, Bathurst, <mark>Henry<\/mark>, third Earl Bathurst. In: ODNB, Bd....","fid":"note__4"}]},{"docId":"Aachen_Prot_14","docUri":"Aachen_Prot_14.html","score":1,"contexts":[{"form":"Henry","weight":"1","pos":505,"context":"...zu seiner Person Norgate, Severn, Wellesley, <mark>Henry<\/mark>, first Baron Cowley. In: ODNB, Bd....","fid":"note__4"}]},{"docId":"Aachen_Prot_43","docUri":"Aachen_Prot_43.html","score":1,"contexts":[{"form":"Henry","weight":"1","pos":607,"context":"...vgl. zu seiner Person Thompson, Bathurst, <mark>Henry<\/mark>, third Earl Bathurst. In: ODNB, Bd....","fid":"note__4"}]}]}