{"stem":"infest","instances":[{"docId":"Verona_V_2","docUri":"Verona_V_2.html","score":1,"contexts":[{"form":"infestant","weight":"1","pos":3251,"context":"...Colonies Espagnoles en Amérique par un essaim de pirates <mark>infestant<\/mark> les mers sous divers pavillons connus et inconnus....","fid":"p__22"}]},{"docId":"Aachen_Prot_32","docUri":"Aachen_Prot_32.html","score":1,"contexts":[{"form":"infestent","weight":"1","pos":4502,"context":"...se trouvent menacés par la multitude de pirates qui <mark>infestent<\/mark> l’océan à la faveur des troubles qui agitent les...","fid":"p__23"}]}]}