{"stem":"jouissent","instances":[{"docId":"Troppau_Prot_2","docUri":"Troppau_Prot_2.html","score":1,"contexts":[{"form":"jouissent","weight":"1","pos":2759,"context":"...en grande partie l’existence paisible et honorable dont elles <mark>jouissent<\/mark> aujourd’hui.","fid":"p__35"}]},{"docId":"Verona_II_1","docUri":"Verona_II_1.html","score":1,"contexts":[{"form":"jouissent","weight":"1","pos":1204,"context":"...ce même Souverain qu’ils ont outragé, tous ne <mark>jouissent<\/mark> près de la Nation d’aucune espèce d’influence ; mais...","fid":"p__18"}]},{"docId":"Troppau_Prot_4","docUri":"Troppau_Prot_4.html","score":1,"contexts":[{"form":"jouissent","weight":"1","pos":172,"context":"Que l’avantage dont <mark>jouissent<\/mark> Mrs Monsieurs les Ministres de ces trois Cabinets par...","fid":"p__20"}]},{"docId":"Verona_III_2","docUri":"Verona_III_2.html","score":1,"contexts":[{"form":"jouissent","weight":"1","pos":798,"context":"...que tels Souverains, Ses Alliés, qui ne <mark>jouissent<\/mark> pas encore de ce privilège, pourront désirer de...","fid":"p__13"}]},{"docId":"Verona_II_5","docUri":"Verona_II_5.html","score":1,"contexts":[{"form":"jouissent","weight":"1","pos":873,"context":"...les autres à se préserver de malheurs semblables, <mark>jouissent<\/mark> au sein de la paix des résultats de Leurs...","fid":"p__21"}]}]}