{"stem":"karl","instances":[{"docId":"Aachen_Prot_32","docUri":"Aachen_Prot_32.html","score":10,"contexts":[{"form":"Karl","weight":"1","pos":1139,"context":"...und 21. Dezember 1818 vakant; anschließend übernahm Anton <mark>Karl<\/mark> Fürst Pálffy von Eröd (*1793) den Posten...","fid":"p__28"},{"form":"Karl","weight":"1","pos":5432,"context":"...und 21. Dezember 1818 vakant; anschließend übernahm Anton <mark>Karl<\/mark> Fürst Pálffy von Eröd (*1793) den Posten...","fid":"note__3"},{"form":"Karl","weight":"1","pos":5551,"context":"...und 21. Dezember 1818 vakant; anschließend übernahm Anton <mark>Karl<\/mark> Fürst Pálffy von Eröd (*1793) den Posten...","fid":"note__4"},{"form":"Karl","weight":"1","pos":5940,"context":"35Vgl. zu seiner Person Weech, <mark>Karl<\/mark> Ludwig Friedrich, Großherzog von Baden. In: ADB...","fid":"note__4"},{"form":"Karl","weight":"1","pos":6230,"context":"...vgl. zu seiner Person Paul, Reinhard, <mark>Karl<\/mark> Friedrich Graf von. In: NDB, Bd. 21, S....","fid":"note__4"},{"form":"Karl","weight":"1","pos":6236,"context":"...Bd. 21, S. 355–357; Gross (Hg.), <mark>Karl<\/mark> Friedrich Reinhard; Delinière, Ein deutscher Aufklärer....","fid":"note__4"},{"form":"Karl","weight":"1","pos":6358,"context":"...Geborene Herzogin zu Mecklenburg-Strelitz, Ehefrau von <mark>Karl<\/mark> Alexander Fürst von Thurn und Taxis (1770–...","fid":"note__4"},{"form":"Karl","weight":"1","pos":6539,"context":"...Baden; vgl. zu seiner Person Wiedenmann, <mark>Karl<\/mark> August Varnhange von Ense; Greiling, Varnhagen von...","fid":"note__4"},{"form":"Karl","weight":"1","pos":6751,"context":"...Geborene Herzogin zu Mecklenburg-Strelitz, Ehefrau von <mark>Karl<\/mark> Alexander Fürst von Thurn und Taxis (1770–...","fid":"note__4"},{"form":"Karl","weight":"1","pos":6773,"context":"92Vgl. zu seiner Person Weech, <mark>Karl<\/mark> Ludwig Friedrich, Großherzog von Baden. In: ADB...","fid":"note__4"}]},{"docId":"Aachen_Prot_20","docUri":"Aachen_Prot_20.html","score":8,"contexts":[{"form":"Karl","weight":"1","pos":2653,"context":"...einliegenden Observations préliminaires sind vom 1817 verstorbenen badischen Innenminister <mark>Karl<\/mark> Wilhelm Marschall von Biberstein unterzeichnet.","fid":"note__7"},{"form":"Karl","weight":"1","pos":2818,"context":"...Louise von Baden, verheiratet, einer Schwester Großherzogs <mark>Karl<\/mark> von Baden.","fid":"note__17"},{"form":"Karl","weight":"1","pos":3120,"context":"37Vgl. zu seiner Person Weech, <mark>Karl<\/mark> Ludwig Friedrich, Großherzog von Baden. In: ADB...","fid":"note__4"},{"form":"Karl","weight":"1","pos":3193,"context":"...vgl. zu seiner Person Körner, Berckheim, <mark>Karl<\/mark> Christian Freiherr von. In: NDB, Bd. 2, S....","fid":"note__4"},{"form":"Karl","weight":"1","pos":3235,"context":"...Baden; vgl. zu seiner Person Gerteis, <mark>Karl<\/mark> Friedrich von Baden. In: NDB, Bd. 11,...","fid":"note__4"},{"form":"Karl","weight":"1","pos":3243,"context":"...S. 221–223; Wiegand, Nieß (Hg.), <mark>Karl<\/mark> Friedrich von Baden.","fid":"note__4"},{"form":"Karl","weight":"1","pos":3376,"context":"55Vgl. zu seiner Person Weech, <mark>Karl<\/mark> Ludwig Friedrich, Großherzog von Baden. In: ADB...","fid":"note__4"},{"form":"Karl","weight":"1","pos":3454,"context":"...vgl. zu seiner Person Körner, Berckheim, <mark>Karl<\/mark> Christian Freiherr von. In: NDB, Bd. 2, S....","fid":"note__4"}]},{"docId":"Aachen_Prot_28","docUri":"Aachen_Prot_28.html","score":6,"contexts":[{"form":"Karl","weight":"1","pos":4126,"context":"24Vgl. zu seiner Person Weech, <mark>Karl<\/mark> Ludwig Friedrich, Großherzog von Baden. In: ADB...","fid":"note__4"},{"form":"Karl","weight":"1","pos":4215,"context":"...29Vgl. zu seiner Person Weech, Sigmund <mark>Karl<\/mark> Johann Freiherr von Reizenstein. In: ADB, Bd....","fid":"note__4"},{"form":"Karl","weight":"1","pos":4222,"context":"...ADB, Bd. 30, S. 69–70; Ders., Sigmund <mark>Karl<\/mark> Johann von Reizenstein. In: Badische Biographien, Bd....","fid":"note__4"},{"form":"Karl","weight":"1","pos":4306,"context":"35Vgl. zu seiner Person Weech, <mark>Karl<\/mark> Ludwig Friedrich, Großherzog von Baden. In: ADB...","fid":"note__4"},{"form":"Karl","weight":"1","pos":4354,"context":"...38Vgl. zu seiner Person Weech, Sigmund <mark>Karl<\/mark> Johann Freiherr von Reizenstein. In: ADB, Bd....","fid":"note__4"},{"form":"Karl","weight":"1","pos":4361,"context":"...ADB, Bd. 30, S. 69–70; Ders., Sigmund <mark>Karl<\/mark> Johann von Reizenstein. In: Badische Biographien, Bd....","fid":"note__4"}]},{"docId":"Aachen_Prot_41","docUri":"Aachen_Prot_41.html","score":4,"contexts":[{"form":"Karl","weight":"1","pos":3757,"context":"27Vgl. zu seiner Person Weech, <mark>Karl<\/mark> Ludwig Friedrich, Großherzog von Baden. In: ADB...","fid":"note__4"},{"form":"Karl","weight":"1","pos":3893,"context":"...vgl. zu seiner Person Körner, Berckheim, <mark>Karl<\/mark> Christian Freiherr von. In: NDB, Bd. 2, S....","fid":"note__4"},{"form":"Karl","weight":"1","pos":4053,"context":"48Vgl. zu seiner Person Weech, <mark>Karl<\/mark> Ludwig Friedrich, Großherzog von Baden. In: ADB...","fid":"note__4"},{"form":"Karl","weight":"1","pos":4167,"context":"...vgl. zu seiner Person Körner, Berckheim, <mark>Karl<\/mark> Christian Freiherr von. In: NDB, Bd. 2, S....","fid":"note__4"}]},{"docId":"Verona_V_2","docUri":"Verona_V_2.html","score":2,"contexts":[{"form":"Karl","weight":"1","pos":4683,"context":"...vgl. zu seiner Person Schlitter, Vincent, <mark>Karl<\/mark> Freiherr von. In: ADB, Bd. 39, S 732...","fid":"note__4"},{"form":"Karl","weight":"1","pos":4870,"context":"...vgl. zu seiner Person Schlitter, Vincent, <mark>Karl<\/mark> Freiherr von. In: ADB, Bd. 39, S 732...","fid":"note__4"}]},{"docId":"Aachen_Prot_1","docUri":"Aachen_Prot_1.html","score":2,"contexts":[{"form":"Karl","weight":"1","pos":333,"context":"2<mark>Karl<\/mark> August Fürst Hardenberg war auf dem Großen Markt Nr....","fid":"note__5"},{"form":"Karl","weight":"1","pos":536,"context":"...vgl. zu seiner Person Schlitter, Vincent, <mark>Karl<\/mark> Freiherr von. In: ADB, Bd. 39, S 732...","fid":"note__4"}]},{"docId":"Aachen_Prot_9","docUri":"Aachen_Prot_9.html","score":2,"contexts":[{"form":"Karl","weight":"1","pos":326,"context":"11Vgl. zu seiner Person Weech, <mark>Karl<\/mark> Ludwig Friedrich, Großherzog von Baden. In: ADB...","fid":"note__4"},{"form":"Karl","weight":"1","pos":381,"context":"15Vgl. zu seiner Person Weech, <mark>Karl<\/mark> Ludwig Friedrich, Großherzog von Baden. In: ADB...","fid":"note__4"}]},{"docId":"Aachen_Prot_14","docUri":"Aachen_Prot_14.html","score":2,"contexts":[{"form":"Karl","weight":"1","pos":458,"context":"17Vgl. zu seiner Person Weech, <mark>Karl<\/mark> Ludwig Friedrich, Großherzog von Baden. In: ADB...","fid":"note__4"},{"form":"Karl","weight":"1","pos":655,"context":"31Vgl. zu seiner Person Weech, <mark>Karl<\/mark> Ludwig Friedrich, Großherzog von Baden. In: ADB...","fid":"note__4"}]},{"docId":"Aachen_Prot_31","docUri":"Aachen_Prot_31.html","score":2,"contexts":[{"form":"Karl","weight":"1","pos":10163,"context":"72Als <mark>Karl<\/mark> II. zwischen 1814 und 1818 auch König von Norwegen...","fid":"note__4"},{"form":"Karl","weight":"1","pos":10295,"context":"82Als <mark>Karl<\/mark> II. zwischen 1814 und 1818 auch König von Norwegen...","fid":"note__4"}]},{"docId":"Aachen_Prot_10","docUri":"Aachen_Prot_10.html","score":2,"contexts":[{"form":"Karl","weight":"1","pos":1156,"context":"18Vgl. zu seiner Person Weech, <mark>Karl<\/mark> Ludwig Friedrich, Großherzog von Baden. In: ADB...","fid":"note__4"},{"form":"Karl","weight":"1","pos":1225,"context":"23Vgl. zu seiner Person Weech, <mark>Karl<\/mark> Ludwig Friedrich, Großherzog von Baden. In: ADB...","fid":"note__4"}]},{"docId":"Aachen_Prot_11","docUri":"Aachen_Prot_11.html","score":2,"contexts":[{"form":"Karl","weight":"1","pos":1112,"context":"12Vgl. zu seiner Person Weech, <mark>Karl<\/mark> Ludwig Friedrich, Großherzog von Baden. In: ADB...","fid":"note__4"},{"form":"Karl","weight":"1","pos":1177,"context":"16Vgl. zu seiner Person Weech, <mark>Karl<\/mark> Ludwig Friedrich, Großherzog von Baden. In: ADB...","fid":"note__4"}]},{"docId":"Laibach_Prot_12","docUri":"Laibach_Prot_12.html","score":1,"contexts":[{"form":"Karl","weight":"1","pos":1014,"context":"...vgl. zu seiner Person Schlitter, Vincent, <mark>Karl<\/mark> Freiherr von. In: ADB, Bd. 39, S 732...","fid":"note__4"}]},{"docId":"Laibach_Prot_3","docUri":"Laibach_Prot_3.html","score":1,"contexts":[{"form":"Karl","weight":"1","pos":572,"context":"...vgl. zu seiner Person Schlitter, Vincent, <mark>Karl<\/mark> Freiherr von. In: ADB, Bd. 39, S 732...","fid":"note__4"}]},{"docId":"Verona_VIII_1","docUri":"Verona_VIII_1.html","score":1,"contexts":[{"form":"Karl","weight":"1","pos":234,"context":"...vgl. zu seiner Person Schlitter, Vincent, <mark>Karl<\/mark> Freiherr von. In: ADB, Bd. 39, S 732...","fid":"note__4"}]},{"docId":"Laibach_Prot_1","docUri":"Laibach_Prot_1.html","score":1,"contexts":[{"form":"Karl","weight":"1","pos":995,"context":"...vgl. zu seiner Person Schlitter, Vincent, <mark>Karl<\/mark> Freiherr von. In: ADB, Bd. 39, S 732...","fid":"note__4"}]},{"docId":"Laibach_Prot_13","docUri":"Laibach_Prot_13.html","score":1,"contexts":[{"form":"Karl","weight":"1","pos":1227,"context":"...vgl. zu seiner Person Schlitter, Vincent, <mark>Karl<\/mark> Freiherr von. In: ADB, Bd. 39, S 732...","fid":"note__4"}]},{"docId":"Laibach_Prot_14","docUri":"Laibach_Prot_14.html","score":1,"contexts":[{"form":"Karl","weight":"1","pos":1178,"context":"...vgl. zu seiner Person Schlitter, Vincent, <mark>Karl<\/mark> Freiherr von. In: ADB, Bd. 39, S 732...","fid":"note__4"}]},{"docId":"Laibach_Prot_5","docUri":"Laibach_Prot_5.html","score":1,"contexts":[{"form":"Karl","weight":"1","pos":646,"context":"...vgl. zu seiner Person Schlitter, Vincent, <mark>Karl<\/mark> Freiherr von. In: ADB, Bd. 39, S 732...","fid":"note__4"}]},{"docId":"Laibach_Prot_6","docUri":"Laibach_Prot_6.html","score":1,"contexts":[{"form":"Karl","weight":"1","pos":765,"context":"...vgl. zu seiner Person Schlitter, Vincent, <mark>Karl<\/mark> Freiherr von. In: ADB, Bd. 39, S 732...","fid":"note__4"}]},{"docId":"Laibach_Prot_11","docUri":"Laibach_Prot_11.html","score":1,"contexts":[{"form":"Karl","weight":"1","pos":1532,"context":"...vgl. zu seiner Person Schlitter, Vincent, <mark>Karl<\/mark> Freiherr von. In: ADB, Bd. 39, S 732...","fid":"note__4"}]},{"docId":"Laibach_Prot_4","docUri":"Laibach_Prot_4.html","score":1,"contexts":[{"form":"Karl","weight":"1","pos":1240,"context":"...vgl. zu seiner Person Schlitter, Vincent, <mark>Karl<\/mark> Freiherr von. In: ADB, Bd. 39, S 732...","fid":"note__4"}]},{"docId":"Laibach_Prot_7","docUri":"Laibach_Prot_7.html","score":1,"contexts":[{"form":"Karl","weight":"1","pos":458,"context":"...vgl. zu seiner Person Schlitter, Vincent, <mark>Karl<\/mark> Freiherr von. In: ADB, Bd. 39, S 732...","fid":"note__4"}]},{"docId":"Laibach_Prot_16","docUri":"Laibach_Prot_16.html","score":1,"contexts":[{"form":"Karl","weight":"1","pos":6590,"context":"...vgl. zu seiner Person Schlitter, Vincent, <mark>Karl<\/mark> Freiherr von. In: ADB, Bd. 39, S 732...","fid":"note__4"}]},{"docId":"Aachen_Prot_49","docUri":"Aachen_Prot_49.html","score":1,"contexts":[{"form":"Karl","weight":"1","pos":294,"context":"...vgl. zu seiner Person Schlitter, Vincent, <mark>Karl<\/mark> Freiherr von. In: ADB, Bd. 39, S 732...","fid":"note__4"}]},{"docId":"Verona_II_8","docUri":"Verona_II_8.html","score":1,"contexts":[{"form":"Karl","weight":"1","pos":1095,"context":"...vgl. zu seiner Person Schlitter, Vincent, <mark>Karl<\/mark> Freiherr von. In: ADB, Bd. 39, S 732...","fid":"note__4"}]},{"docId":"Aachen_Prot_44","docUri":"Aachen_Prot_44.html","score":1,"contexts":[{"form":"Karl","weight":"1","pos":636,"context":"...vgl. zu seiner Person Schlitter, Vincent, <mark>Karl<\/mark> Freiherr von. In: ADB, Bd. 39, S 732...","fid":"note__4"}]},{"docId":"Verona_I_18","docUri":"Verona_I_18.html","score":1,"contexts":[{"form":"Karl","weight":"1","pos":132,"context":"...vgl. zu seiner Person Schlitter, Vincent, <mark>Karl<\/mark> Freiherr von. In: ADB, Bd. 39, S 732...","fid":"note__4"}]},{"docId":"Laibach_Prot_2","docUri":"Laibach_Prot_2.html","score":1,"contexts":[{"form":"Karl","weight":"1","pos":450,"context":"...vgl. zu seiner Person Schlitter, Vincent, <mark>Karl<\/mark> Freiherr von. In: ADB, Bd. 39, S 732...","fid":"note__4"}]},{"docId":"Laibach_Prot_15","docUri":"Laibach_Prot_15.html","score":1,"contexts":[{"form":"Karl","weight":"1","pos":522,"context":"...vgl. zu seiner Person Schlitter, Vincent, <mark>Karl<\/mark> Freiherr von. In: ADB, Bd. 39, S 732...","fid":"note__4"}]},{"docId":"Aachen_Prot_26","docUri":"Aachen_Prot_26.html","score":1,"contexts":[{"form":"Karl","weight":"1","pos":4929,"context":"...Geborene Herzogin zu Mecklenburg-Strelitz, Ehefrau von <mark>Karl<\/mark> Alexander Fürst von Thurn und Taxis (1770–...","fid":"note__4"}]},{"docId":"Verona_I_15","docUri":"Verona_I_15.html","score":1,"contexts":[{"form":"Karl","weight":"1","pos":610,"context":"...vgl. zu seiner Person Schlitter, Vincent, <mark>Karl<\/mark> Freiherr von. In: ADB, Bd. 39, S 732...","fid":"note__4"}]},{"docId":"Laibach_Prot_8","docUri":"Laibach_Prot_8.html","score":1,"contexts":[{"form":"Karl","weight":"1","pos":2437,"context":"...vgl. zu seiner Person Schlitter, Vincent, <mark>Karl<\/mark> Freiherr von. In: ADB, Bd. 39, S 732...","fid":"note__4"}]},{"docId":"Laibach_Prot_10","docUri":"Laibach_Prot_10.html","score":1,"contexts":[{"form":"Karl","weight":"1","pos":672,"context":"...vgl. zu seiner Person Schlitter, Vincent, <mark>Karl<\/mark> Freiherr von. In: ADB, Bd. 39, S 732...","fid":"note__4"}]},{"docId":"Laibach_Prot_9","docUri":"Laibach_Prot_9.html","score":1,"contexts":[{"form":"Karl","weight":"1","pos":5797,"context":"...vgl. zu seiner Person Schlitter, Vincent, <mark>Karl<\/mark> Freiherr von. In: ADB, Bd. 39, S 732...","fid":"note__4"}]}]}