{"stem":"l'entreprendr","instances":[{"docId":"Troppau_Prot_3","docUri":"Troppau_Prot_3.html","score":1,"contexts":[{"form":"l’entreprendre","weight":"1","pos":975,"context":"...difficulté de cet important travail, et il n’ose <mark>l’entreprendre<\/mark> qu’en choisissant pour point de départ les transactions qui...","fid":"p__10"}]},{"docId":"Troppau_Prot_5","docUri":"Troppau_Prot_5.html","score":1,"contexts":[{"form":"l’entreprendre","weight":"1","pos":843,"context":"...nouvelle guerre, aux alliés la pénible nécessité de <mark>l’entreprendre<\/mark>.","fid":"p__17"}]}]}