{"stem":"lamb","instances":[{"docId":"Aachen_Prot_32","docUri":"Aachen_Prot_32.html","score":1,"contexts":[{"form":"Lamb","weight":"1","pos":6249,"context":"...M端nchen; vgl. zu seiner Person Reynolds, <mark>Lamb<\/mark>, Frederick James. In: ODNB, Bd. 32,...","fid":"note__4"}]},{"docId":"Aachen_Prot_36","docUri":"Aachen_Prot_36.html","score":1,"contexts":[{"form":"Lamb","weight":"1","pos":701,"context":"...M端nchen; vgl. zu seiner Person Reynolds, <mark>Lamb<\/mark>, Frederick James. In: ODNB, Bd. 32,...","fid":"note__4"}]},{"docId":"Aachen_Prot_41","docUri":"Aachen_Prot_41.html","score":1,"contexts":[{"form":"Lamb","weight":"1","pos":3972,"context":"...M端nchen; vgl. zu seiner Person Reynolds, <mark>Lamb<\/mark>, Frederick James. In: ODNB, Bd. 32,...","fid":"note__4"}]},{"docId":"Aachen_Prot_26","docUri":"Aachen_Prot_26.html","score":1,"contexts":[{"form":"Lamb","weight":"1","pos":4674,"context":"...M端nchen; vgl. zu seiner Person Reynolds, <mark>Lamb<\/mark>, Frederick James. In: ODNB, Bd. 32,...","fid":"note__4"}]}]}