{"stem":"luglio","instances":[{"docId":"Laibach_Prot_6","docUri":"Laibach_Prot_6.html","score":1,"contexts":[{"form":"Luglio","weight":"1","pos":273,"context":"...giudicano gli avvenimenti accaduti in Napoli dal 2 di <mark>Luglio<\/mark> 2 fino a questo giorno. Le ho trovate...","fid":"p__14"}]},{"docId":"Verona_II_7","docUri":"Verona_II_7.html","score":1,"contexts":[{"form":"Luglio","weight":"1","pos":1745,"context":"...Nostro Signore Papa Pio Settimo in Data de 6 <mark>Luglio<\/mark> 1816 sulla organizzazione dell’amministrazione pubblica (Mailand 1816)....","fid":"note__5"}]}]}