{"stem":"matter","instances":[{"docId":"Troppau_Prot_7","docUri":"Troppau_Prot_7.html","score":4,"contexts":[{"form":"matter","weight":"1","pos":630,"context":"It left them in fact no other <mark>matter<\/mark> for Deliberation than what might belong in good Faith...","fid":"p__13"},{"form":"matter","weight":"1","pos":1147,"context":"...that Occupation, which devolves upon them not as <mark>matter<\/mark> of Option, but as a Duty under existing...","fid":"p__31"},{"form":"matter","weight":"1","pos":1794,"context":"...can, a priori, be made the subject <mark>matter<\/mark> of an Alliance between the Great Powers of Europe...","fid":"p__38"},{"form":"matter","weight":"1","pos":3727,"context":"...Nation and Nation can never properly be made a <mark>matter<\/mark> of written stipulation or be assumed as the Attribute...","fid":"p__41"}]}]}