{"stem":"mettant","instances":[{"docId":"Verona_II_1","docUri":"Verona_II_1.html","score":1,"contexts":[{"form":"mettant","weight":"1","pos":3032,"context":"...publique ne pouvait être négligée par le Gouvernement : <mark>mettant<\/mark> de côté ces moyens trop connus et presqu’usés avec...","fid":"p__59"}]},{"docId":"Laibach_Prot_16","docUri":"Laibach_Prot_16.html","score":1,"contexts":[{"form":"mettant","weight":"1","pos":547,"context":"...qu’inspire le véritable amour de la patrie, et <mark>mettant<\/mark> à la place des devoirs connus les prétextes arbitraires...","fid":"p__9"}]},{"docId":"Aachen_Prot_25","docUri":"Aachen_Prot_25.html","score":1,"contexts":[{"form":"mettant","weight":"1","pos":697,"context":"...sincèrement pénétrés du désir d’accomplir un saint devoir en <mark>mettant<\/mark> fin aux horreurs de la Traite.","fid":"p__16"}]},{"docId":"Verona_II_4","docUri":"Verona_II_4.html","score":1,"contexts":[{"form":"mettant","weight":"1","pos":308,"context":"En <mark>mettant<\/mark> à exécution cet ordre de son Souverain, Mr...","fid":"p__16"}]}]}