{"stem":"mie","instances":[{"docId":"Laibach_Prot_6","docUri":"Laibach_Prot_6.html","score":2,"contexts":[{"form":"mie","weight":"1","pos":502,"context":"...mantenimento della pace generale; e che risulti dalle <mark>mie<\/mark> sollecitudini e dai miei sforzi un sistema di governo...","fid":"p__13"},{"form":"mie","weight":"1","pos":576,"context":"...l’effetto che mi permettono d’aspettarne tanto la coscienza delle <mark>mie<\/mark> paterne intenzioni, quanto la fiducia nei vostri lumi...","fid":"p__14"}]}]}