{"stem":"montevideo","instances":[{"docId":"Aachen_Prot_14","docUri":"Aachen_Prot_14.html","score":1,"contexts":[{"form":"Montevideo","weight":"1","pos":167,"context":"...les Ministres Médiateurs au sujet de la restitution de <mark>Montevideo<\/mark>.6 Les deux projets ayant été approuvés tels...","fid":"p__22"}]},{"docId":"Aachen_Prot_12","docUri":"Aachen_Prot_12.html","score":1,"contexts":[{"form":"Montevideo","weight":"1","pos":62,"context":"...l’Espagne et le Portugal au sujet de l’occupation de <mark>Montevideo<\/mark>. Mrs. Messieurs les Ministres ont résolu d’adresser...","fid":"p__32"}]},{"docId":"Aachen_Prot_10","docUri":"Aachen_Prot_10.html","score":1,"contexts":[{"form":"Montevideo","weight":"1","pos":251,"context":"...qui ont eu lieu à Paris sur l’affaire de <mark>Montevideo<\/mark> 3 ; et","fid":"p__14"}]}]}