{"stem":"paris","instances":[{"docId":"Laibach_Prot_11","docUri":"Laibach_Prot_11.html","score":1,"contexts":[{"form":"Pariser","weight":"1","pos":1178,"context":"...ist die Besatzung Frankreichs nach den Bestimmungen des Zweiten <mark>Pariser<\/mark> Friedens vom 20. November 1815.","fid":"note__6"}]},{"docId":"Aachen_Prot_23","docUri":"Aachen_Prot_23.html","score":1,"contexts":[{"form":"Pariser","weight":"1","pos":2142,"context":"...10Londoner Botschafterkonferenz, eingerichtet auf Grundlage des Zweiten <mark>Pariser<\/mark> Friedens vom 20. November 1815.","fid":"note__8"}]}]}