{"stem":"plénip","instances":[{"docId":"Aachen_Prot_28","docUri":"Aachen_Prot_28.html","score":2,"contexts":[{"form":"Plénip","weight":"1","pos":1751,"context":"Le  <mark>Plénip<\/mark>. Plénipotentiaire Badois admet cependant encore le principe d’une...","fid":"p__33"},{"form":"Plénip","weight":"1","pos":1885,"context":"...la cession territoriale. Nous avons fait entrevoir au  <mark>Plénip<\/mark>. Plénipotentiaire Badois la possibilité d’une adhésion de notre...","fid":"p__37"}]},{"docId":"Aachen_Prot_16","docUri":"Aachen_Prot_16.html","score":1,"contexts":[{"form":"Plénip","weight":"1","pos":462,"context":"...Dans la Séance du 19 Oct. Octobre le  <mark>Plénip<\/mark> Plénipotentiaire Autrichien a proposé que cet article fût rédigé...","fid":"note__10"}]}]}