{"stem":"prescrib","instances":[{"docId":"Troppau_Prot_7","docUri":"Troppau_Prot_7.html","score":2,"contexts":[{"form":"prescribed","weight":"1","pos":1927,"context":"...fulfil with Zeal and Promptitude those Duties which are <mark>prescribed<\/mark> to Him by the Treaties so happily subsisting between...","fid":"p__42"},{"form":"prescribed","weight":"1","pos":2366,"context":"...manner and under the same reserve as has been <mark>prescribed<\/mark> to Your Excellency at Troppau; and it will...","fid":"p__20"}]}]}