{"stem":"respir","instances":[{"docId":"Laibach_Prot_6","docUri":"Laibach_Prot_6.html","score":1,"contexts":[{"form":"respire","weight":"1","pos":45,"context":"...franchise et à la noble confiance que cette lettre <mark>respire<\/mark>.","fid":"p__24"}]},{"docId":"Verona_IX_1","docUri":"Verona_IX_1.html","score":1,"contexts":[{"form":"respire","weight":"1","pos":3090,"context":"...les peuples, tant qu’une faction antisociale qui ne <mark>respire<\/mark> que révolution et bouleversement, soit qu’elle marche à...","fid":"p__25"}]},{"docId":"Laibach_Prot_9","docUri":"Laibach_Prot_9.html","score":1,"contexts":[{"form":"respirent","weight":"1","pos":3081,"context":"...Naples par l’ascendant des vues généreuses et pures que <mark>respirent<\/mark> tous les actes sur lesquels elle se fonde....","fid":"p__26"}]}]}