{"stem":"settl","instances":[{"docId":"Troppau_Prot_7","docUri":"Troppau_Prot_7.html","score":2,"contexts":[{"form":"settled","weight":"1","pos":933,"context":"...was given that the Territorial System of Europe as <mark>settled<\/mark> by late Treaties was not thereby intended to be...","fid":"p__24"},{"form":"settle","weight":"1","pos":4139,"context":"...how hopeless on the other hand the attempt to <mark>settle<\/mark> by Foreign Arms or by Foreign Influence alone any...","fid":"p__53"}]},{"docId":"Verona_I_6","docUri":"Verona_I_6.html","score":1,"contexts":[{"form":"settled","weight":"1","pos":133,"context":"...the throne, to overturn that which had been <mark>settled<\/mark>, and which he had guaranteed, or to...","fid":"p__5"}]},{"docId":"Verona_I_17","docUri":"Verona_I_17.html","score":1,"contexts":[{"form":"settled","weight":"1","pos":114,"context":"It was <mark>settled<\/mark>, that the notes to be prepared according to...","fid":"p__19"}]}]}