{"stem":"sénégal","instances":[{"docId":"Aachen_Prot_30","docUri":"Aachen_Prot_30.html","score":2,"contexts":[{"form":"Sénégal","weight":"1","pos":1748,"context":"...instructions nouvelles ont été envoyées aux Autorités françaises du <mark>Sénégal<\/mark> pour qu’elles eussent à redoubler d’activité contre tout Commerce...","fid":"p__22"},{"form":"Sénégal","weight":"1","pos":1777,"context":"...foi implicite aux rapports parvenus contre les Autorités du <mark>Sénégal<\/mark>. Ces rapports, qui les impliquent d’une manière...","fid":"p__22"}]}]}