{"stem":"tyranniqu","instances":[{"docId":"Verona_I_21","docUri":"Verona_I_21.html","score":1,"contexts":[{"form":"tyrannique","weight":"1","pos":351,"context":"...violence, et un moyen de couvrir ce système <mark>tyrannique<\/mark> d’une apparence légale. L’on n’hésita plus à abolir...","fid":"p__14"}]},{"docId":"Troppau_Prot_5","docUri":"Troppau_Prot_5.html","score":1,"contexts":[{"form":"tyrannique","weight":"1","pos":2084,"context":"..., le délivreroit également d’un pouvoir nouveau non moins <mark>tyrannique<\/mark> et non moins désastreux du pouvoir, du crime...","fid":"p__9"}]}]}