{"stem":"tätigkeit","instances":[{"docId":"Aachen_Prot_12","docUri":"Aachen_Prot_12.html","score":1,"contexts":[{"form":"Tätigkeit","weight":"1","pos":148,"context":"...S. 156–160, wo der Autor die <mark>Tätigkeit<\/mark> der Botschafterkonferenz in Hinblick auf den Konflikt zwischen Spanien...","fid":"note__5"}]},{"docId":"Aachen_Prot_48","docUri":"Aachen_Prot_48.html","score":1,"contexts":[{"form":"Tätigkeit","weight":"1","pos":237,"context":"...S. 156–160, wo der Autor die <mark>Tätigkeit<\/mark> der Botschafterkonferenz in Hinblick auf den Konflikt zwischen Spanien...","fid":"note__4"}]}]}