{"stem":"vit","instances":[{"docId":"Verona_I_22","docUri":"Verona_I_22.html","score":1,"contexts":[{"form":"vit","weight":"1","pos":379,"context":"...de deuil si malheureusement reproduits en Espagne, on <mark>vit<\/mark> le 7 Juillet 5 le sang couler jusque dans...","fid":"p__22"}]},{"docId":"Laibach_Prot_16","docUri":"Laibach_Prot_16.html","score":1,"contexts":[{"form":"vit","weight":"1","pos":2978,"context":"...respect et de l’affection de ces sujets, se <mark>vit<\/mark> forcé de descendre d’un trône qu’il avait orné par...","fid":"p__19"}]}]}